{"termTheme":"dark","layouts":{"layout-1":{"data":{"layout-restorer:data":{"main":{"dock":{"type":"split-area","orientation":"horizontal","children":[{"type":"split-area","orientation":"vertical","children":[{"type":"tab-area","widgets":["notebook:Guide.ipynb"],"currentIndex":0},{"type":"tab-area","widgets":["terminal:1"],"currentIndex":0}],"sizes":[0.5,0.5]},{"type":"tab-area","widgets":["editor:setup_node.sh","editor:reactnd-contacts-server/server.js","editor:reactnd-contacts-server/config.js","editor:reactnd-contacts-server/package.json"],"currentIndex":1}],"sizes":[0.47776183644189385,0.5222381635581063]}}}}}}}